setup.cfg
setup.py
deploy/__init__.py
deploy/docker_machine.py
deploy/entry.py
deploy/project.py
deploy/settings.py
deploy/user_config.py
deploy/commands/__init__.py
deploy/commands/create.py
deploy/commands/destroy.py
deploy/commands/project.py
deploy/commands/secret.py
deploy/commands/secret_clone.py
deploy/commands/update.py
deploy/commands/addons/__init__.py
deploy/commands/addons/create.py
deploy/commands/addons/destroy.py
deploy/commands/addons/entry.py
deploy/commands/addons/update.py
deploy/commands/deis/__init__.py
deploy/commands/deis/configure_dns.py
deploy/commands/deis/create.py
deploy/commands/deis/create_admin.py
deploy/commands/deis/destroy.py
deploy/commands/deis/entry.py
deploy/commands/main/__init__.py
deploy/commands/main/configure_dns.py
deploy/commands/main/create.py
deploy/commands/main/destroy.py
deploy/commands/main/entry.py
deploy/commands/main/update.py
deploy/secret/__init__.py
deploy/secret/exceptions.py
deploy/secret/secret_dir.py
deploy/secret/store.py
deploy/utils/__init__.py
deploy/utils/click_utils.py
deploy/utils/decorators.py
deploy/utils/path_utils.py
deploy/utils/subprocess_utils.py
deploy/utils/utils.py
tigerhost_deploy.egg-info/PKG-INFO
tigerhost_deploy.egg-info/SOURCES.txt
tigerhost_deploy.egg-info/dependency_links.txt
tigerhost_deploy.egg-info/entry_points.txt
tigerhost_deploy.egg-info/requires.txt
tigerhost_deploy.egg-info/top_level.txt