Metadata-Version: 1.0
Name: tigerhost-deploy
Version: 0.2.0
Summary: A tool for provisioning TigerHost.
Home-page: https://github.com/naphatkrit/TigerHost
Author: Naphat Sanguansin
Author-email: naphat.krit@gmail.com
License: UNKNOWN
Platform: UNKNOWN
